.gitignore
index.yaml
pyproject.toml
readme.md
setup.cfg
setup.py
examples/create_batch.py
examples/google_queue_manager.py
examples/google_storage_worker.py
examples/post_job_to_local_worker.py
examples/post_job_to_queue.py
kws_pipeline/__init__.py
kws_pipeline.egg-info/PKG-INFO
kws_pipeline.egg-info/SOURCES.txt
kws_pipeline.egg-info/dependency_links.txt
kws_pipeline.egg-info/requires.txt
kws_pipeline.egg-info/top_level.txt
kws_pipeline/google_helpers/__init__.py
kws_pipeline/google_helpers/bucket_manager.py
kws_pipeline/google_helpers/job_model.py
kws_pipeline/google_helpers/middlewares.py
kws_pipeline/google_helpers/settings.py
kws_pipeline/google_helpers/task_logger.py
kws_pipeline/google_helpers/task_manager.py
kws_pipeline/queue/__init__.py
kws_pipeline/queue/abc.py
kws_pipeline/queue/schema.py
kws_pipeline/queue/utils.py
kws_pipeline/workers/__init__.py
kws_pipeline/workers/queue_manager.py
kws_pipeline/workers/storage_manager.py
kws_pipeline/workers/worker.py